{
   "prefix":{
      "prov":"http://www.w3.org/ns/prov",
      "cf":"http://www.camflow.org"
   },
   "activity":{
      "cf:AgAAAAAAAAAp8QAAAAAAAEtEbsIAAX8AEQAAAAAAAAA=":{
         "cf:node_info":{
            "cf:type":2,
            "cf:id":61737,
            "cf:boot_id":3262006347,
            "cf:machine_id":8323328,
            "cf:version":17
         },
         "cf:user_id":1000,
         "cf:group_id":1000
      },
      "cf:AgAAAAAAAAAp8QAAAAAAAEtEbsIAAX8AEgAAAAAAAAA=":{
         "cf:node_info":{
            "cf:type":2,
            "cf:id":61737,
            "cf:boot_id":3262006347,
            "cf:machine_id":8323328,
            "cf:version":18
         },
         "cf:user_id":1000,
         "cf:group_id":1000
      }
   },
   "entity":{
      "cf:AwAAAAAAAABaIwAAAAAAAEtEbsIBAAAABwAAAAAAAAA=":{
         "cf:node_info":{
            "cf:type":3,
            "cf:id":9050,
            "cf:boot_id":3262006347,
            "cf:machine_id":1,
            "cf:version":7
         },
         "cf:user_id":0,
         "cf:group_id":0,
         "prov:type":"cf:file",
         "cf:mode":"0X00B6",
         "cf:uuid":"49233bb2-12b9-bef3-147a-8fd8ab75286d"
      },
      "cf:AwAAAAAAAABaIwAAAAAAAEtEbsIBAAAACAAAAAAAAAA=":{
         "cf:node_info":{
            "cf:type":3,
            "cf:id":9050,
            "cf:boot_id":3262006347,
            "cf:machine_id":1,
            "cf:version":8
         },
         "cf:user_id":0,
         "cf:group_id":0,
         "prov:type":"cf:file",
         "cf:mode":"0X00B6",
         "cf:uuid":"49233bb2-12b9-bef3-147a-8fd8ab75286d"
      }
   },
   "used":{
      "cf:AQAAAAAAAAAtAAAAAAAAAEtEbsIAAX8AEAAAAAAAAAA=":{
         "cf:edge_info":{
            "cf:type":1,
            "cf:id":45,
            "cf:boot_id":3262006347,
            "cf:machine_id":8323328
         },
         "cf:type":"open",
         "cf:allowed":true,
         "prov:entity":"cf:AwAAAAAAAABaIwAAAAAAAEtEbsIBAAAABwAAAAAAAAA=",
         "prov:activity":"cf:AgAAAAAAAAAp8QAAAAAAAEtEbsIAAX8AEQAAAAAAAAA="
      },
      "cf:AQAAAAAAAAAxAAAAAAAAAEtEbsIAAX8AEQAAAAAAAAA=":{
         "cf:edge_info":{
            "cf:type":1,
            "cf:id":49,
            "cf:boot_id":3262006347,
            "cf:machine_id":8323328
         },
         "cf:type":"read",
         "cf:allowed":true,
         "prov:entity":"cf:AwAAAAAAAAAu8QAAAAAAAEtEbsIAAX8AAAAAAAAAAAA=",
         "prov:activity":"cf:AgAAAAAAAAAp8QAAAAAAAEtEbsIAAX8AEgAAAAAAAAA="
      }
   },
   "wasInformedBy":{
      "cf:Abk0gf////8sAAAAAAAAAEtEbsIAAX8AWiMAAAAAAAA=":{
         "cf:edge_info":{
            "cf:type":1,
            "cf:id":44,
            "cf:boot_id":3262006347,
            "cf:machine_id":8323328
         },
         "cf:type":"version",
         "cf:allowed":true,
         "prov:informant":"cf:AgAAAAAAAAAp8QAAAAAAAEtEbsIAAX8AEAAAAAAAAAA=",
         "prov:informed":"cf:AgAAAAAAAAAp8QAAAAAAAEtEbsIAAX8AEQAAAAAAAAA="
      },
      "cf:AQAAAAAAAAAwAAAAAAAAAEtEbsIAAX8ADgGRfACI//8=":{
         "cf:edge_info":{
            "cf:type":1,
            "cf:id":48,
            "cf:boot_id":3262006347,
            "cf:machine_id":8323328
         },
         "cf:type":"version",
         "cf:allowed":true,
         "prov:informant":"cf:AgAAAAAAAAAp8QAAAAAAAEtEbsIAAX8AEQAAAAAAAAA=",
         "prov:informed":"cf:AgAAAAAAAAAp8QAAAAAAAEtEbsIAAX8AEgAAAAAAAAA="
      }
   },
   "wasDerivedFrom":{
      "cf:AQAAAAAAAAApAAAAAAAAAEtEbsIAAX8AAAAAAAAAAAA=":{
         "cf:edge_info":{
            "cf:type":1,
            "cf:id":41,
            "cf:boot_id":3262006347,
            "cf:machine_id":8323328
         },
         "cf:type":"write",
         "cf:allowed":true,
         "prov:usedEntity":"cf:AgAAAAAAAAAp8QAAAAAAAEtEbsIAAX8AEAAAAAAAAAA=",
         "prov:generatedEntity":"cf:AwAAAAAAAAA38QAAAAAAAEtEbsIAAX8AAQAAAAAAAAA="
      },
      "cf:AfuRfACI//8qAAAAAAAAAEtEbsIAAX8Afrk0gf////8=":{
         "cf:edge_info":{
            "cf:type":1,
            "cf:id":42,
            "cf:boot_id":3262006347,
            "cf:machine_id":8323328
         },
         "cf:type":"version",
         "cf:allowed":true,
         "prov:usedEntity":"cf:AwAAAAAAAABaIwAAAAAAAEtEbsIBAAAABgAAAAAAAAA=",
         "prov:generatedEntity":"cf:AwAAAAAAAABaIwAAAAAAAEtEbsIBAAAABwAAAAAAAAA="
      },
      "cf:AQAAAAAAAAArAAAAAAAAAEtEbsIAAX8ABgAAAAAAAAA=":{
         "cf:edge_info":{
            "cf:type":1,
            "cf:id":43,
            "cf:boot_id":3262006347,
            "cf:machine_id":8323328
         },
         "cf:type":"write",
         "cf:allowed":true,
         "prov:usedEntity":"cf:AgAAAAAAAAAp8QAAAAAAAEtEbsIAAX8AEAAAAAAAAAA=",
         "prov:generatedEntity":"cf:AwAAAAAAAABaIwAAAAAAAEtEbsIBAAAABwAAAAAAAAA="
      },
      "cf:Af2RfACI//8uAAAAAAAAAEtEbsIAAX8A9Jskgf////8=":{
         "cf:edge_info":{
            "cf:type":1,
            "cf:id":46,
            "cf:boot_id":3262006347,
            "cf:machine_id":8323328
         },
         "cf:type":"version",
         "cf:allowed":true,
         "prov:usedEntity":"cf:AwAAAAAAAABaIwAAAAAAAEtEbsIBAAAABwAAAAAAAAA=",
         "prov:generatedEntity":"cf:AwAAAAAAAABaIwAAAAAAAEtEbsIBAAAACAAAAAAAAAA="
      },
      "cf:AQAAAAAAAAAvAAAAAAAAAEtEbsIAAX8ABwAAAAAAAAA=":{
         "cf:edge_info":{
            "cf:type":1,
            "cf:id":47,
            "cf:boot_id":3262006347,
            "cf:machine_id":8323328
         },
         "cf:type":"write",
         "cf:allowed":true,
         "prov:usedEntity":"cf:AgAAAAAAAAAp8QAAAAAAAEtEbsIAAX8AEQAAAAAAAAA=",
         "prov:generatedEntity":"cf:AwAAAAAAAABaIwAAAAAAAEtEbsIBAAAACAAAAAAAAAA="
      }
   }
}